chromedriver_py/__init__.py
chromedriver_py/chromedriver_linux64
chromedriver_py/chromedriver_mac-arm64
chromedriver_py/chromedriver_mac-x64
chromedriver_py/chromedriver_win32.exe
chromedriver_py/chromedriver_win64.exe
chromedriver_py-143.0.7499.192.dist-info/licenses/LICENSE
chromedriver_py-143.0.7499.192.dist-info/METADATA
chromedriver_py-143.0.7499.192.dist-info/WHEEL
chromedriver_py-143.0.7499.192.dist-info/top_level.txt
chromedriver_py-143.0.7499.192.dist-info/RECORD
