Metadata-Version: 2.4
Name: chromedriver-py
Version: 143.0.7499.192
Summary: chromedriver binaries for all platforms
Home-page: http://github.com/breuerfelix/chromedriver-py
Author: Felix Breuer
Author-email: fbreuer@pm.me
Keywords: chromedriver cross-platform binaries binary
Classifier: License :: OSI Approved :: Apache Software License
Classifier: Programming Language :: Python
Classifier: Operating System :: OS Independent
License-File: LICENSE
Dynamic: author
Dynamic: author-email
Dynamic: classifier
Dynamic: description
Dynamic: description-content-type
Dynamic: home-page
Dynamic: keywords
Dynamic: license-file
Dynamic: summary
